setup.py
gradergen/RegexParser.py
gradergen/__init__.py
gradergen/grader_generator.py
gradergen/structures.py
gradergen.egg-info/PKG-INFO
gradergen.egg-info/SOURCES.txt
gradergen.egg-info/dependency_links.txt
gradergen.egg-info/entry_points.txt
gradergen.egg-info/top_level.txt
gradergen/languages/C.py
gradergen/languages/CPP.py
gradergen/languages/__init__.py
gradergen/languages/fast_input.pas
gradergen/languages/fast_io.c
gradergen/languages/fast_io.cpp
gradergen/languages/fast_output.pas
gradergen/languages/pascal.py