Metadata-Version: 1.0
Name: gradergen
Version: 0.3
Summary: Grader generator
Home-page: UNKNOWN
Author: UNKNOWN
Author-email: UNKNOWN
License: UNKNOWN
Platform: UNKNOWN
